web_heath_checker/__init__.py
web_heath_checker/__main__.py
web_health_checker_script-0.1.5.dist-info/METADATA
web_health_checker_script-0.1.5.dist-info/WHEEL
web_health_checker_script-0.1.5.dist-info/entry_points.txt
web_health_checker_script-0.1.5.dist-info/top_level.txt
web_health_checker_script-0.1.5.dist-info/RECORD
